{
  "Harley (James) Davidson": {
    "PetName": "Harley (James) Davidson",
    "PetType": "Dog",
    "PetTypeScore": 1.0,
    "Breed": "Biewer Terrier",
    "BreedScore": 1.0,
    "LifeStage": "10",
    "LifeStageScore": 1.0,
    "Gender": "MALE",
    "GenderScore": 1.0,
    "SizeCategory": "UNK",
    "SizeScore": 0.0,
    "Weight": "11",
    "WeightScore": 1.0,
    "PersonalityTraits": [
      "UNK"
    ],
    "PersonalityScores": {
      "UNK": 0.0
    },
    "FavoriteProductCategories": [
      "Dog Food",
      "Dog Flea Treatment"
    ],
    "CategoryScores": {
      "Dog Food": 0.9,
      "Dog Flea Treatment": 0.9
    },
    "BrandPreferences": [
      "Primal",
      "Stella & Chewy's",
      "Bravecto",
      "Heartgard Plus"
    ],
    "BrandScores": {
      "Primal": 0.9,
      "Stella & Chewy's": 0.9,
      "Bravecto": 0.9,
      "Heartgard Plus": 0.9
    },
    "DietaryPreferences": [
      "Grain-Free",
      "Raw Freeze-Dried"
    ],
    "DietaryScores": {
      "Grain-Free": 0.9,
      "Raw Freeze-Dried": 0.9
    },
    "BehavioralCues": [
      "UNK"
    ],
    "BehavioralScores": {
      "UNK": 0.0
    },
    "HealthMentions": [
      "UNK"
    ],
    "HealthScores": {
      "UNK": 0.0
    },
    "MostOrderedProducts": [
      "Bravecto Chew for Dogs, 9.9-22 lbs, (Orange Box), 1 Chew (12-wks. supply)",
      "Primal Beef Formula Nuggets Grain-Free Raw Freeze-Dried Dog Food, 14-oz bag",
      "Primal Chicken Formula Nuggets Grain-Free Raw Freeze-Dried Dog Food, 14-oz bag",
      "Stella & Chewy's Duck Duck Goose Dinner Patties Freeze-Dried Raw Dog Food, 14-oz bag",
      "Stella & Chewy's Tantalizing Turkey Dinner Patties Freeze-Dried Raw Dog Food, 14-oz bag"
    ],
    "confidence_score": 0.8333333333333334,
    "name": "Harley (James) Davidson"
  },
  "The Princess Monaco": {
    "PetName": "The Princess Monaco",
    "PetType": "Dog",
    "PetTypeScore": 1.0,
    "Breed": "Biewer Terrier",
    "BreedScore": 1.0,
    "LifeStage": "12",
    "LifeStageScore": 1.0,
    "Gender": "FMLE",
    "GenderScore": 1.0,
    "SizeCategory": "Small",
    "SizeScore": 0.9,
    "Weight": "6",
    "WeightScore": 1.0,
    "PersonalityTraits": [
      "UNK"
    ],
    "PersonalityScores": {
      "UNK": 0.0
    },
    "FavoriteProductCategories": [
      "Dog Food",
      "Dog Flea Treatment"
    ],
    "CategoryScores": {
      "Dog Food": 0.9,
      "Dog Flea Treatment": 0.8
    },
    "BrandPreferences": [
      "Primal",
      "Stella & Chewy's",
      "Bravecto",
      "Heartgard Plus"
    ],
    "BrandScores": {
      "Primal": 0.9,
      "Stella & Chewy's": 0.8,
      "Bravecto": 0.8,
      "Heartgard Plus": 0.7
    },
    "DietaryPreferences": [
      "Grain-Free",
      "Raw",
      "Freeze-Dried"
    ],
    "DietaryScores": {
      "Grain-Free": 0.9,
      "Raw": 0.9,
      "Freeze-Dried": 0.9
    },
    "BehavioralCues": [
      "UNK"
    ],
    "BehavioralScores": {
      "UNK": 0.0
    },
    "HealthMentions": [
      "UNK"
    ],
    "HealthScores": {
      "UNK": 0.0
    },
    "MostOrderedProducts": [
      "Bravecto Chew for Dogs, 9.9-22 lbs, (Orange Box), 1 Chew (12-wks. supply)",
      "Primal Beef Formula Nuggets Grain-Free Raw Freeze-Dried Dog Food, 14-oz bag",
      "Primal Chicken Formula Nuggets Grain-Free Raw Freeze-Dried Dog Food, 14-oz bag",
      "Stella & Chewy's Duck Duck Goose Dinner Patties Freeze-Dried Raw Dog Food, 14-oz bag",
      "Stella & Chewy's Tantalizing Turkey Dinner Patties Freeze-Dried Raw Dog Food, 14-oz bag"
    ],
    "confidence_score": 0.9833333333333334,
    "name": "The Princess Monaco"
  },
  "cust_confidence_score": 0.9083333333333334,
  "gets_playback": true,
  "gets_personalized": true
}