{
  "Abby": {
    "PetName": "Abby",
    "PetType": "Dog",
    "PetTypeScore": 1.0,
    "Breed": "Boxer",
    "BreedScore": 1.0,
    "LifeStage": "4",
    "LifeStageScore": 1.0,
    "Gender": "FMLE",
    "GenderScore": 1.0,
    "SizeCategory": "UNK",
    "SizeScore": 0.0,
    "Weight": "60",
    "WeightScore": 1.0,
    "PersonalityTraits": [
      "food-motivated",
      "affectionate"
    ],
    "PersonalityScores": {
      "food-motivated": 0.9,
      "affectionate": 0.7
    },
    "FavoriteProductCategories": [
      "food",
      "treats"
    ],
    "CategoryScores": {
      "food": 0.9,
      "treats": 0.8
    },
    "BrandPreferences": [
      "Diamond Naturals",
      "Blue Buffalo"
    ],
    "BrandScores": {
      "Diamond Naturals": 0.9,
      "Blue Buffalo": 0.8
    },
    "DietaryPreferences": [
      "lamb-based",
      "balanced diet"
    ],
    "DietaryScores": {
      "lamb-based": 0.9,
      "balanced diet": 0.8
    },
    "BehavioralCues": [
      "enjoys treats"
    ],
    "BehavioralScores": {
      "enjoys treats": 0.8
    },
    "HealthMentions": [
      "healthy"
    ],
    "HealthScores": {
      "healthy": 0.8
    },
    "MostOrderedProducts": [
      "Diamond Naturals Large Breed Adult Lamb Meal & Rice Formula Dry Dog Food, 40-lb bag",
      "Blue Buffalo Health Bars Baked with Bacon, Egg & Cheese Dog Treats, 16-oz bag"
    ],
    "ConfidenceScore": 0.0,
    "confidence_score": 0.8333333333333334
  },
  "Finnley (Finn)": {
    "PetName": "Finnley (Finn)",
    "PetType": "Dog",
    "PetTypeScore": 1.0,
    "Breed": "Boxer",
    "BreedScore": 1.0,
    "LifeStage": "3",
    "LifeStageScore": 1.0,
    "Gender": "MALE",
    "GenderScore": 1.0,
    "SizeCategory": "UNK",
    "SizeScore": 0.0,
    "Weight": "60",
    "WeightScore": 1.0,
    "PersonalityTraits": [
      "food-motivated",
      "affectionate"
    ],
    "PersonalityScores": {
      "food-motivated": 0.9,
      "affectionate": 0.7
    },
    "FavoriteProductCategories": [
      "food",
      "treats"
    ],
    "CategoryScores": {
      "food": 0.9,
      "treats": 0.8
    },
    "BrandPreferences": [
      "Diamond Naturals",
      "Blue Buffalo"
    ],
    "BrandScores": {
      "Diamond Naturals": 0.9,
      "Blue Buffalo": 0.8
    },
    "DietaryPreferences": [
      "lamb-based",
      "balanced diet"
    ],
    "DietaryScores": {
      "lamb-based": 0.9,
      "balanced diet": 0.8
    },
    "BehavioralCues": [
      "enjoys treats"
    ],
    "BehavioralScores": {
      "enjoys treats": 0.8
    },
    "HealthMentions": [
      "healthy"
    ],
    "HealthScores": {
      "healthy": 0.8
    },
    "MostOrderedProducts": [
      "Diamond Naturals Large Breed Adult Lamb Meal & Rice Formula Dry Dog Food, 40-lb bag",
      "Blue Buffalo Health Bars Baked with Bacon, Egg & Cheese Dog Treats, 16-oz bag"
    ],
    "ConfidenceScore": 0.0,
    "confidence_score": 0.8333333333333334
  },
  "cust_confidence_score": 0.8333333333333334,
  "gets_playback": true,
  "gets_personalized": false
}